blochsimulator-1.0.9.dist-info/WHEEL
blochsimulator-1.0.9.dist-info/entry_points.txt
blochsimulator-1.0.9.dist-info/top_level.txt
blochsimulator-1.0.9.dist-info/METADATA
blochsimulator-1.0.9.dist-info/RECORD
blochsimulator/bloch_core.h
blochsimulator/notebook_exporter.py
blochsimulator/phantom_widget.py
blochsimulator/kspace.py
blochsimulator/kspace_widget.py
blochsimulator/bloch_core_modified.c
blochsimulator/pulse_loader.py
blochsimulator/bloch_wrapper.c
blochsimulator/simulator.py
blochsimulator/slice_explorer.py
blochsimulator/phantom.py
blochsimulator/blochsimulator_cy.cpython-310-x86_64-linux-gnu.so
blochsimulator/visualization.py
blochsimulator/gui_phantom_integration.py
blochsimulator/gui.py
blochsimulator/spectral_phantom.py
blochsimulator/bloch_wrapper.pyx
blochsimulator/__init__.py
blochsimulator.libs/libgomp-a34b3233.so.1.0.0
