Metadata-Version: 2.4
Name: blochsimulator
Version: 1.0.9
Summary: High-performance Bloch equation simulator for MRI
Author: Luca Nagel
License: MIT
Project-URL: Homepage, https://github.com/LucaNagel/bloch_sim_gui
Requires-Python: >=3.9
Requires-Dist: numpy>=1.20.0
Requires-Dist: scipy>=1.7.0
Requires-Dist: matplotlib>=3.3.0
Requires-Dist: cython>=0.29.0
Requires-Dist: h5py>=3.0.0
Provides-Extra: gui
Requires-Dist: PyQt5>=5.15.0; extra == "gui"
Requires-Dist: pyqtgraph>=0.12.0; extra == "gui"
Requires-Dist: PyOpenGL>=3.1.0; extra == "gui"
Provides-Extra: export
Requires-Dist: imageio>=2.34.0; extra == "export"
Requires-Dist: imageio-ffmpeg>=0.4.9; extra == "export"
Requires-Dist: nbformat>=5.0.0; extra == "export"
